training/__init__.py
training/config.py
training/summary.py
training/trainer.py
meta_outliers-1.0.0.dist-info/LICENSE
meta_outliers-1.0.0.dist-info/METADATA
meta_outliers-1.0.0.dist-info/WHEEL
meta_outliers-1.0.0.dist-info/top_level.txt
meta_outliers-1.0.0.dist-info/RECORD
